traffic_light_controller/traffic_light_controller.sv
module traffic_light_controller(
	input clk, rst,
	output reg [2:0]f1,
	output reg [2:0]f2,
	output reg [2:0]f3,
	output reg [2:0]f4,
	
	output reg [2:0]r1,
	output reg [2:0]r2,
	output reg [2:0]r3,
	output reg [2:0]r4,
	
	output reg [2:0]l1,
	output reg [2:0]l2,
	output reg [2:0]l3,
	output reg [2:0]l4,
	
	output reg [2:0]c1,
	output reg [2:0]c2,
	output reg [2:0]c3,
	output reg [2:0]c4
);

parameter red = 3'b100, yellow = 3'b010, green = 3'b001;

typedef enum{
	initialize,
	
	s1_red,
	s1_yellow_up,
	s1_yellow_down,	
	s1_green,
	
	s2_red,
	s2_yellow_up,
	s2_yellow_down,
	s2_green,
	
	s3_red,
	s3_yellow_up,
	s3_yellow_down,
	s3_green,
	
	s4_red,
	s4_yellow_up,
	s4_yellow_down,
	s4_green,
	
	s5_red,
	s5_yellow_up,
	s5_yellow_down,
	s5_green,
	
	s6_red,
	s6_yellow_up,
	s6_yellow_down,
	s6_green
} traffic_light_t;

reg [5:0] count;
reg [19:0] day_time;
traffic_light_t current_state;

always_ff@(posedge clk or negedge rst) 
begin
	if(!rst)
	begin
		count <= 0;
		current_state <= initialize;
	end
	else
	begin 
		count <= count + 1;
		day_time <= day_time + 1;
		if (day_time > 500)
		begin
		day_time <= 0;
		end
		
		case(current_state)
		initialize:
		if (count > 2)
			begin
			current_state <= s1_yellow_down;
			count <= 1;
			end
			
		s1_yellow_down:
		if (count > 0)
			begin
			current_state <= s1_green;
			count <= 1;
			end
			
		s1_green:
		if (count > 10 && (day_time > 250 && day_time < 350) )
			begin
			current_state <= s1_yellow_up;
			count <= 1;
			end
			
		else if (count > 20)
			begin
			current_state <= s1_yellow_up;
			count <= 1;
			end
			
		s1_yellow_up:
		if (count > 2)
			begin
			current_state <= s1_red;
			count <= 1;
			end
			
		s1_red:
		if (count > 1)
			begin
			current_state <= s2_yellow_down;
			count <= 1;
			end
			
		s2_yellow_down:
		if (count > 1)
			begin
			current_state <= s2_green;
			count <= 1;
			end
			
		s2_green:
		if (count > 10)
			begin
			current_state <= s2_yellow_up;
			count <= 1;
			end
			
		s2_yellow_up:
		if (count > 2)
			begin
			current_state <= s2_red;
			count <= 1;
			end
			
		s2_red:
		if (count > 1)
			begin
			current_state <= s3_yellow_down;
			count <= 1;
			end
			
		s3_yellow_down:
		if (count > 1)
			begin
			current_state <= s3_green;
			count <= 1;
			end
			
		s3_green:
		if (count > 10)
			begin
			current_state <= s3_yellow_up;
			count <= 1;
			end
			
		s3_yellow_up:
		if (count > 2)
			begin
			current_state <= s3_red;
			count <= 1;
			end
			
		s3_red:
		if (count > 1)
			begin
			current_state <= s4_yellow_down;
			count <= 1;
			end
			
		s4_yellow_down:
		if (count > 1)
			begin
			current_state <= s4_green;
			count <= 1;
			end
			
		s4_green:
		if (count > 10)
			begin
			current_state <= s4_yellow_up;
			count <= 1;
			end
			
		s4_yellow_up:
		if (count > 2)
			begin
			current_state <= s4_red;
			count <= 1;
			end
			
		s4_red:
		if (count > 1)
			begin
			current_state <= s5_yellow_down;
			count <= 1;
			end
			
		s5_yellow_down:
		if (count > 1)
			begin
			current_state <= s5_green;
			count <= 1;
			end
			
		s5_green:
		if (count > 10)
			begin
			current_state <= s5_yellow_up;
			count <= 1;
			end
			
		s5_yellow_up:
		if (count > 2)
			begin
			current_state <= s5_red;
			count <= 1;
			end
			
		s5_red:
		if (count > 1)
			begin
			current_state <= s6_yellow_down;
			count <= 1;
			end
			
		s6_yellow_down:
		if (count > 1)
			begin
			current_state <= s6_green;
			count <= 1;
			end
			
		s6_green:
		if (count > 10)
			begin
			current_state <= s6_yellow_up;
			count <= 1;
			end
			
		s6_yellow_up:
		if (count > 2)
			begin
			current_state <= s6_red;
			count <= 1;
			end
			
		s6_red:
		if (count > 1)
			begin
			current_state <= s1_yellow_down;
			count <= 1;
			end
		endcase
	end
end	
			
always_comb
begin
   {f1, f2, f3, f4, r1, r2, r3, r4, l1, l2, l3, l4, c1, c2, c3, c4} = {16{red}};

	case(current_state)
		initialize, s1_red, s3_red, s4_red, s6_red:
		begin
		{f1, f2, f3, f4, r1, r2, r3, r4, l1, l2, l3, l4, c1, c2, c3, c4} = {16{red}};
		end
		
		s1_yellow_down, s1_yellow_up:
		begin
		{f1, f3} = {2{yellow}};
		end
		
		s1_green:
		begin
		{f1, f3, c2, c4} = {4{green}};
		end
		
		s2_yellow_down:
		begin
		{l2, l4, l3, r3} = {4{yellow}};
		end
		
		s2_yellow_up:
		begin
		{l2, r3} = {2{yellow}};
		{l4, l3} = {2{green}};
		end
		
		s2_green:
		begin
		{l2, l4, l3, r3} = {4{green}};
		end
		
		s3_yellow_down:
		begin
		{l1, r4} = {2{yellow}};
		{l3, l4} = {2{green}};
		end
		
		s2_red:
		begin
		{l3, l4} = {2{green}};
		end
		
		s5_red:
		begin
		{l1, l2} = {2{green}};
		end
		
		s3_green:
		begin
		{l1, l3, l4, r4} = {4{green}};
		end
		
		s3_yellow_up:
		begin
		{l1, l3, l4, r4} = {4{yellow}};
		end
		
		s4_yellow_down, s4_yellow_up:
		begin
		{f2, f4} = {2{yellow}};
		end
		
		s4_green:
		begin
		{c1, c3, f2, f4} = {4{green}};
		end
		
		s5_yellow_up:
		begin
		{l4, r1} = {2{green}};
		{l2, l1} = {2{green}};
		end
		
		s5_green:
		begin
		{l2, l1, l4, r1} = {4{green}};
		end
		
		s5_yellow_down:
		begin
		{l2, l1, l4, r1} = {4{yellow}};
		end
		
		s6_yellow_down:
		begin
		{l3, r2} = {2{yellow}};
		{l1, l2} = {2{green}};
		end
		
		s6_yellow_up:
		begin
		{l1, l3, l2, r2} = {4{yellow}};
		end
		
		s6_green:
		begin
		{l1, l3, l2, r2} = {4{green}};
		end
	endcase
end
endmodule

traffic_light_controller/traffic_light_controller_tb.sv
`timescale 1ns / 1ps

module traffic_light_controller_tb;

// Clock and reset signals
reg clk;
reg rst;

// Output signals from DUT
wire [2:0] f1, f2, f3, f4;
wire [2:0] r1, r2, r3, r4;
wire [2:0] l1, l2, l3, l4;
wire [2:0] c1, c2, c3, c4;

// Instantiate the Device Under Test (DUT)
traffic_light_controller dut (
    .clk(clk),
    .rst(rst),
    .f1(f1), .f2(f2), .f3(f3), .f4(f4),
    .r1(r1), .r2(r2), .r3(r3), .r4(r4),
    .l1(l1), .l2(l2), .l3(l3), .l4(l4),
    .c1(c1), .c2(c2), .c3(c3), .c4(c4)
);

// Clock generation
initial begin
    clk = 0;
    forever #5 clk = ~clk; // 10ns period (100MHz)
end

// Test sequence
initial begin
    $dumpfile("traffic_light_tb.vcd");
    $dumpvars(0, traffic_light_controller_tb);
    
    // Initialize
    rst = 0;
    #20;
    
    // Release reset and observe operation
    rst = 1;
    
    // Run simulation for enough time to see multiple state transitions
    #2000;
    
    // Test reset during operation
    rst = 0;
    #20;
    rst = 1;
    #1000;
    
    $display("Testbench completed successfully");
    $finish;
end

// Monitor to display state changes
always @(posedge clk) begin
    $display("Time: %0t | State: %s | f1:%b f2:%b f3:%b f4:%b | Count: %0d", 
             $time, dut.current_state.name(), f1, f2, f3, f4, dut.count);
end

endmodule

traffic_light_controller/traffic_light_tb.vcd
$date
	Wed Aug 13 13:00:43 2025
$end
$version
	ModelSim Version 2020.1
$end
$timescale
	1ps
$end

$scope module traffic_light_controller_tb $end
$var reg 1 ! clk $end
$var reg 1 " rst $end
$var wire 1 # f1 [2] $end
$var wire 1 $ f1 [1] $end
$var wire 1 % f1 [0] $end
$var wire 1 & f2 [2] $end
$var wire 1 ' f2 [1] $end
$var wire 1 ( f2 [0] $end
$var wire 1 ) f3 [2] $end
$var wire 1 * f3 [1] $end
$var wire 1 + f3 [0] $end
$var wire 1 , f4 [2] $end
$var wire 1 - f4 [1] $end
$var wire 1 . f4 [0] $end
$var wire 1 / r1 [2] $end
$var wire 1 0 r1 [1] $end
$var wire 1 1 r1 [0] $end
$var wire 1 2 r2 [2] $end
$var wire 1 3 r2 [1] $end
$var wire 1 4 r2 [0] $end
$var wire 1 5 r3 [2] $end
$var wire 1 6 r3 [1] $end
$var wire 1 7 r3 [0] $end
$var wire 1 8 r4 [2] $end
$var wire 1 9 r4 [1] $end
$var wire 1 : r4 [0] $end
$var wire 1 ; l1 [2] $end
$var wire 1 < l1 [1] $end
$var wire 1 = l1 [0] $end
$var wire 1 > l2 [2] $end
$var wire 1 ? l2 [1] $end
$var wire 1 @ l2 [0] $end
$var wire 1 A l3 [2] $end
$var wire 1 B l3 [1] $end
$var wire 1 C l3 [0] $end
$var wire 1 D l4 [2] $end
$var wire 1 E l4 [1] $end
$var wire 1 F l4 [0] $end
$var wire 1 G c1 [2] $end
$var wire 1 H c1 [1] $end
$var wire 1 I c1 [0] $end
$var wire 1 J c2 [2] $end
$var wire 1 K c2 [1] $end
$var wire 1 L c2 [0] $end
$var wire 1 M c3 [2] $end
$var wire 1 N c3 [1] $end
$var wire 1 O c3 [0] $end
$var wire 1 P c4 [2] $end
$var wire 1 Q c4 [1] $end
$var wire 1 R c4 [0] $end

$scope module dut $end
$var parameter 3 S red $end
$var parameter 3 T yellow $end
$var parameter 3 U green $end
$var wire 1 V clk $end
$var wire 1 W rst $end
$var reg 3 X f1 [2:0] $end
$var reg 3 Y f2 [2:0] $end
$var reg 3 Z f3 [2:0] $end
$var reg 3 [ f4 [2:0] $end
$var reg 3 \ r1 [2:0] $end
$var reg 3 ] r2 [2:0] $end
$var reg 3 ^ r3 [2:0] $end
$var reg 3 _ r4 [2:0] $end
$var reg 3 ` l1 [2:0] $end
$var reg 3 a l2 [2:0] $end
$var reg 3 b l3 [2:0] $end
$var reg 3 c l4 [2:0] $end
$var reg 3 d c1 [2:0] $end
$var reg 3 e c2 [2:0] $end
$var reg 3 f c3 [2:0] $end
$var reg 3 g c4 [2:0] $end
$var reg 6 h count [5:0] $end
$var reg 20 i day_time [19:0] $end
$var integer 32 j current_state $end
$upscope $end
$upscope $end
$enddefinitions $end
#0
$dumpvars
0!
0"
b100 X
b100 Y
b100 Z
b100 [
b100 \
b100 ]
b100 ^
b100 _
b100 `
b100 a
b100 b
b100 c
b100 d
b100 e
b100 f
b100 g
b0 h
bx i
b100 S
b10 T
b1 U
b0 j
0%
0$
1#
0(
0'
1&
0+
0*
1)
0.
0-
1,
01
00
1/
04
03
12
07
06
15
0:
09
18
0=
0<
1;
0@
0?
1>
0C
0B
1A
0F
0E
1D
0I
0H
1G
0L
0K
1J
0O
0N
1M
0R
0Q
1P
0V
0W
$end
#5000
1!
1V
#10000
0!
0V
#15000
1!
1V
#20000
1"
0!
1W
0V
#25000
1!
1V
b1 h
#30000
0!
0V
#35000
1!
1V
b10 h
#40000
0!
0V
#45000
1!
1V
b11 h
#50000
0!
0V
#55000
1!
1V
b100 h
b11 j
b1 h
b10 Z
b10 X
1$
0#
1*
0)
#60000
0!
0V
#65000
1!
1V
b10 h
b100 j
b1 h
b100 Z
b100 X
b1 g
b1 e
b1 Z
b1 X
1L
0J
1R
0P
1%
0$
1+
0*
#70000
0!
0V
#75000
1!
1V
b10 h
#80000
0!
0V
#85000
1!
1V
b11 h
#90000
0!
0V
#95000
1!
1V
b100 h
#100000
0!
0V
#105000
1!
1V
b101 h
#110000
0!
0V
#115000
1!
1V
b110 h
#120000
0!
0V
#125000
1!
1V
b111 h
#130000
0!
0V
#135000
1!
1V
b1000 h
#140000
0!
0V
#145000
1!
1V
b1001 h
#150000
0!
0V
#155000
1!
1V
b1010 h
#160000
0!
0V
#165000
1!
1V
b1011 h
#170000
0!
0V
#175000
1!
1V
b1100 h
#180000
0!
0V
#185000
1!
1V
b1101 h
#190000
0!
0V
#195000
1!
1V
b1110 h
#200000
0!
0V
#205000
1!
1V
b1111 h
#210000
0!
0V
#215000
1!
1V
b10000 h
#220000
0!
0V
#225000
1!
1V
b10001 h
#230000
0!
0V
#235000
1!
1V
b10010 h
#240000
0!
0V
#245000
1!
1V
b10011 h
#250000
0!
0V
#255000
1!
1V
b10100 h
#260000
0!
0V
#265000
1!
1V
b10101 h
#270000
0!
0V
#275000
1!
1V
b10110 h
b10 j
b1 h
b100 g
b100 e
b100 Z
b100 X
b10 Z
b10 X
0%
1$
0+
1*
0L
1J
0R
1P
#280000
0!
0V
#285000
1!
1V
b10 h
#290000
0!
0V
#295000
1!
1V
b11 h
#300000
0!
0V
#305000
1!
1V
b100 h
b1 j
b1 h
b100 Z
b100 X
0$
1#
0*
1)
#310000
0!
0V
#315000
1!
1V
b10 h
#320000
0!
0V
#325000
1!
1V
b11 h
b111 j
b1 h
b10 ^
b10 b
b10 c
b10 a
1?
0>
1E
0D
1B
0A
16
05
#330000
0!
0V
#335000
1!
1V
b10 h
#340000
0!
0V
#345000
1!
1V
b11 h
b1000 j
b1 h
b100 c
b100 b
b100 a
b100 ^
b1 ^
b1 b
b1 c
b1 a
17
06
1@
0?
1C
0B
1F
0E
#350000
0!
0V
#355000
1!
1V
b10 h
#360000
0!
0V
#365000
1!
1V
b11 h
#370000
0!
0V
#375000
1!
1V
b100 h
#380000
0!
0V
#385000
1!
1V
b101 h
#390000
0!
0V
#395000
1!
1V
b110 h
#400000
0!
0V
#405000
1!
1V
b111 h
#410000
0!
0V
#415000
1!
1V
b1000 h
#420000
0!
0V
#425000
1!
1V
b1001 h
#430000
0!
0V
#435000
1!
1V
b1010 h
#440000
0!
0V
#445000
1!
1V
b1011 h
#450000
0!
0V
#455000
1!
1V
b1100 h
b110 j
b1 h
b100 c
b100 b
b100 a
b100 ^
b10 ^
b10 a
b1 b
b1 c
07
16
0@
1?
#460000
0!
0V
#465000
1!
1V
b10 h
#470000
0!
0V
#475000
1!
1V
b11 h
#480000
0!
0V
#485000
1!
1V
b100 h
b101 j
b1 h
b100 c
b100 b
b100 a
b100 ^
b1 c
b1 b
06
15
0?
1>
#490000
0!
0V
#495000
1!
1V
b10 h
#500000
0!
0V
#505000
1!
1V
b11 h
b1011 j
b1 h
b100 c
b100 b
b10 _
b10 `
b1 c
b1 b
1<
0;
19
08
#510000
0!
0V
#515000
1!
1V
b10 h
#520000
0!
0V
#525000
1!
1V
b11 h
b1100 j
b1 h
b100 c
b100 b
b100 `
b100 _
b1 _
b1 c
b1 b
b1 `
1:
09
1=
0<
#530000
0!
0V
#535000
1!
1V
b10 h
#540000
0!
0V
#545000
1!
1V
b11 h
#550000
0!
0V
#555000
1!
1V
b100 h
#560000
0!
0V
#565000
1!
1V
b101 h
#570000
0!
0V
#575000
1!
1V
b110 h
#580000
0!
0V
#585000
1!
1V
b111 h
#590000
0!
0V
#595000
1!
1V
b1000 h
#600000
0!
0V
#605000
1!
1V
b1001 h
#610000
0!
0V
#615000
1!
1V
b1010 h
#620000
0!
0V
#625000
1!
1V
b1011 h
#630000
0!
0V
#635000
1!
1V
b1100 h
b1010 j
b1 h
b100 c
b100 b
b100 `
b100 _
b10 _
b10 c
b10 b
b10 `
0:
19
0=
1<
0C
1B
0F
1E
#640000
0!
0V
#645000
1!
1V
b10 h
#650000
0!
0V
#655000
1!
1V
b11 h
#660000
0!
0V
#665000
1!
1V
b100 h
b1001 j
b1 h
b100 c
b100 b
b100 `
b100 _
09
18
0<
1;
0B
1A
0E
1D
#670000
0!
0V
#675000
1!
1V
b10 h
#680000
0!
0V
#685000
1!
1V
b11 h
b1111 j
b1 h
b10 [
b10 Y
1'
0&
1-
0,
#690000
0!
0V
#695000
1!
1V
b10 h
#700000
0!
0V
#705000
1!
1V
b11 h
b10000 j
b1 h
b100 [
b100 Y
b1 [
b1 Y
b1 f
b1 d
1I
0G
1O
0M
1(
0'
1.
0-
#710000
0!
0V
#715000
1!
1V
b10 h
#720000
0!
0V
#725000
1!
1V
b11 h
#730000
0!
0V
#735000
1!
1V
b100 h
#740000
0!
0V
#745000
1!
1V
b101 h
#750000
0!
0V
#755000
1!
1V
b110 h
#760000
0!
0V
#765000
1!
1V
b111 h
#770000
0!
0V
#775000
1!
1V
b1000 h
#780000
0!
0V
#785000
1!
1V
b1001 h
#790000
0!
0V
#795000
1!
1V
b1010 h
#800000
0!
0V
#805000
1!
1V
b1011 h
#810000
0!
0V
#815000
1!
1V
b1100 h
b1110 j
b1 h
b100 f
b100 d
b100 [
b100 Y
b10 [
b10 Y
0(
1'
0.
1-
0I
1G
0O
1M
#820000
0!
0V
#825000
1!
1V
b10 h
#830000
0!
0V
#835000
1!
1V
b11 h
#840000
0!
0V
#845000
1!
1V
b100 h
b1101 j
b1 h
b100 [
b100 Y
0'
1&
0-
1,
#850000
0!
0V
#855000
1!
1V
b10 h
#860000
0!
0V
#865000
1!
1V
b11 h
b10011 j
b1 h
b10 \
b10 c
b10 `
b10 a
1?
0>
1<
0;
1E
0D
10
0/
#870000
0!
0V
#875000
1!
1V
b10 h
#880000
0!
0V
#885000
1!
1V
b11 h
b10100 j
b1 h
b100 c
b100 a
b100 `
b100 \
b1 \
b1 c
b1 `
b1 a
11
00
1=
0<
1@
0?
1F
0E
#890000
0!
0V
#895000
1!
1V
b10 h
#900000
0!
0V
#905000
1!
1V
b11 h
#910000
0!
0V
#915000
1!
1V
b100 h
#920000
0!
0V
#925000
1!
1V
b101 h
#930000
0!
0V
#935000
1!
1V
b110 h
#940000
0!
0V
#945000
1!
1V
b111 h
#950000
0!
0V
#955000
1!
1V
b1000 h
#960000
0!
0V
#965000
1!
1V
b1001 h
#970000
0!
0V
#975000
1!
1V
b1010 h
#980000
0!
0V
#985000
1!
1V
b1011 h
#990000
0!
0V
#995000
1!
1V
b1100 h
b10010 j
b1 h
b100 c
b100 a
b100 `
b100 \
b1 \
b1 c
b1 `
b1 a
#1000000
0!
0V
#1005000
1!
1V
b10 h
#1010000
0!
0V
#1015000
1!
1V
b11 h
#1020000
0!
0V
#1025000
1!
1V
b100 h
b10001 j
b1 h
b100 c
b100 a
b100 `
b100 \
b1 a
b1 `
01
1/
0F
1D
#1030000
0!
0V
#1035000
1!
1V
b10 h
#1040000
0!
0V
#1045000
1!
1V
b11 h
b10111 j
b1 h
b100 a
b100 `
b10 ]
b10 b
b1 a
b1 `
1B
0A
13
02
#1050000
0!
0V
#1055000
1!
1V
b10 h
#1060000
0!
0V
#1065000
1!
1V
b11 h
b11000 j
b1 h
b100 b
b100 a
b100 `
b100 ]
b1 ]
b1 a
b1 b
b1 `
14
03
1C
0B
#1070000
0!
0V
#1075000
1!
1V
b10 h
#1080000
0!
0V
#1085000
1!
1V
b11 h
#1090000
0!
0V
#1095000
1!
1V
b100 h
#1100000
0!
0V
#1105000
1!
1V
b101 h
#1110000
0!
0V
#1115000
1!
1V
b110 h
#1120000
0!
0V
#1125000
1!
1V
b111 h
#1130000
0!
0V
#1135000
1!
1V
b1000 h
#1140000
0!
0V
#1145000
1!
1V
b1001 h
#1150000
0!
0V
#1155000
1!
1V
b1010 h
#1160000
0!
0V
#1165000
1!
1V
b1011 h
#1170000
0!
0V
#1175000
1!
1V
b1100 h
b10110 j
b1 h
b100 b
b100 a
b100 `
b100 ]
b10 ]
b10 a
b10 b
b10 `
04
13
0=
1<
0@
1?
0C
1B
#1180000
0!
0V
#1185000
1!
1V
b10 h
#1190000
0!
0V
#1195000
1!
1V
b11 h
#1200000
0!
0V
#1205000
1!
1V
b100 h
b10101 j
b1 h
b100 b
b100 a
b100 `
b100 ]
03
12
0<
1;
0?
1>
0B
1A
#1210000
0!
0V
#1215000
1!
1V
b10 h
#1220000
0!
0V
#1225000
1!
1V
b11 h
b11 j
b1 h
b10 Z
b10 X
1$
0#
1*
0)
#1230000
0!
0V
#1235000
1!
1V
b10 h
b100 j
b1 h
b100 Z
b100 X
b1 g
b1 e
b1 Z
b1 X
1L
0J
1R
0P
1%
0$
1+
0*
#1240000
0!
0V
#1245000
1!
1V
b10 h
#1250000
0!
0V
#1255000
1!
1V
b11 h
#1260000
0!
0V
#1265000
1!
1V
b100 h
#1270000
0!
0V
#1275000
1!
1V
b101 h
#1280000
0!
0V
#1285000
1!
1V
b110 h
#1290000
0!
0V
#1295000
1!
1V
b111 h
#1300000
0!
0V
#1305000
1!
1V
b1000 h
#1310000
0!
0V
#1315000
1!
1V
b1001 h
#1320000
0!
0V
#1325000
1!
1V
b1010 h
#1330000
0!
0V
#1335000
1!
1V
b1011 h
#1340000
0!
0V
#1345000
1!
1V
b1100 h
#1350000
0!
0V
#1355000
1!
1V
b1101 h
#1360000
0!
0V
#1365000
1!
1V
b1110 h
#1370000
0!
0V
#1375000
1!
1V
b1111 h
#1380000
0!
0V
#1385000
1!
1V
b10000 h
#1390000
0!
0V
#1395000
1!
1V
b10001 h
#1400000
0!
0V
#1405000
1!
1V
b10010 h
#1410000
0!
0V
#1415000
1!
1V
b10011 h
#1420000
0!
0V
#1425000
1!
1V
b10100 h
#1430000
0!
0V
#1435000
1!
1V
b10101 h
#1440000
0!
0V
#1445000
1!
1V
b10110 h
b10 j
b1 h
b100 g
b100 e
b100 Z
b100 X
b10 Z
b10 X
0%
1$
0+
1*
0L
1J
0R
1P
#1450000
0!
0V
#1455000
1!
1V
b10 h
#1460000
0!
0V
#1465000
1!
1V
b11 h
#1470000
0!
0V
#1475000
1!
1V
b100 h
b1 j
b1 h
b100 Z
b100 X
0$
1#
0*
1)
#1480000
0!
0V
#1485000
1!
1V
b10 h
#1490000
0!
0V
#1495000
1!
1V
b11 h
b111 j
b1 h
b10 ^
b10 b
b10 c
b10 a
1?
0>
1E
0D
1B
0A
16
05
#1500000
0!
0V
#1505000
1!
1V
b10 h
#1510000
0!
0V
#1515000
1!
1V
b11 h
b1000 j
b1 h
b100 c
b100 b
b100 a
b100 ^
b1 ^
b1 b
b1 c
b1 a
17
06
1@
0?
1C
0B
1F
0E
#1520000
0!
0V
#1525000
1!
1V
b10 h
#1530000
0!
0V
#1535000
1!
1V
b11 h
#1540000
0!
0V
#1545000
1!
1V
b100 h
#1550000
0!
0V
#1555000
1!
1V
b101 h
#1560000
0!
0V
#1565000
1!
1V
b110 h
#1570000
0!
0V
#1575000
1!
1V
b111 h
#1580000
0!
0V
#1585000
1!
1V
b1000 h
#1590000
0!
0V
#1595000
1!
1V
b1001 h
#1600000
0!
0V
#1605000
1!
1V
b1010 h
#1610000
0!
0V
#1615000
1!
1V
b1011 h
#1620000
0!
0V
#1625000
1!
1V
b1100 h
b110 j
b1 h
b100 c
b100 b
b100 a
b100 ^
b10 ^
b10 a
b1 b
b1 c
07
16
0@
1?
#1630000
0!
0V
#1635000
1!
1V
b10 h
#1640000
0!
0V
#1645000
1!
1V
b11 h
#1650000
0!
0V
#1655000
1!
1V
b100 h
b101 j
b1 h
b100 c
b100 b
b100 a
b100 ^
b1 c
b1 b
06
15
0?
1>
#1660000
0!
0V
#1665000
1!
1V
b10 h
#1670000
0!
0V
#1675000
1!
1V
b11 h
b1011 j
b1 h
b100 c
b100 b
b10 _
b10 `
b1 c
b1 b
1<
0;
19
08
#1680000
0!
0V
#1685000
1!
1V
b10 h
#1690000
0!
0V
#1695000
1!
1V
b11 h
b1100 j
b1 h
b100 c
b100 b
b100 `
b100 _
b1 _
b1 c
b1 b
b1 `
1:
09
1=
0<
#1700000
0!
0V
#1705000
1!
1V
b10 h
#1710000
0!
0V
#1715000
1!
1V
b11 h
#1720000
0!
0V
#1725000
1!
1V
b100 h
#1730000
0!
0V
#1735000
1!
1V
b101 h
#1740000
0!
0V
#1745000
1!
1V
b110 h
#1750000
0!
0V
#1755000
1!
1V
b111 h
#1760000
0!
0V
#1765000
1!
1V
b1000 h
#1770000
0!
0V
#1775000
1!
1V
b1001 h
#1780000
0!
0V
#1785000
1!
1V
b1010 h
#1790000
0!
0V
#1795000
1!
1V
b1011 h
#1800000
0!
0V
#1805000
1!
1V
b1100 h
b1010 j
b1 h
b100 c
b100 b
b100 `
b100 _
b10 _
b10 c
b10 b
b10 `
0:
19
0=
1<
0C
1B
0F
1E
#1810000
0!
0V
#1815000
1!
1V
b10 h
#1820000
0!
0V
#1825000
1!
1V
b11 h
#1830000
0!
0V
#1835000
1!
1V
b100 h
b1001 j
b1 h
b100 c
b100 b
b100 `
b100 _
09
18
0<
1;
0B
1A
0E
1D
#1840000
0!
0V
#1845000
1!
1V
b10 h
#1850000
0!
0V
#1855000
1!
1V
b11 h
b1111 j
b1 h
b10 [
b10 Y
1'
0&
1-
0,
#1860000
0!
0V
#1865000
1!
1V
b10 h
#1870000
0!
0V
#1875000
1!
1V
b11 h
b10000 j
b1 h
b100 [
b100 Y
b1 [
b1 Y
b1 f
b1 d
1I
0G
1O
0M
1(
0'
1.
0-
#1880000
0!
0V
#1885000
1!
1V
b10 h
#1890000
0!
0V
#1895000
1!
1V
b11 h
#1900000
0!
0V
#1905000
1!
1V
b100 h
#1910000
0!
0V
#1915000
1!
1V
b101 h
#1920000
0!
0V
#1925000
1!
1V
b110 h
#1930000
0!
0V
#1935000
1!
1V
b111 h
#1940000
0!
0V
#1945000
1!
1V
b1000 h
#1950000
0!
0V
#1955000
1!
1V
b1001 h
#1960000
0!
0V
#1965000
1!
1V
b1010 h
#1970000
0!
0V
#1975000
1!
1V
b1011 h
#1980000
0!
0V
#1985000
1!
1V
b1100 h
b1110 j
b1 h
b100 f
b100 d
b100 [
b100 Y
b10 [
b10 Y
0(
1'
0.
1-
0I
1G
0O
1M
#1990000
0!
0V
#1995000
1!
1V
b10 h
#2000000
0!
0V
#2005000
1!
1V
b11 h
#2010000
0!
0V
#2015000
1!
1V
b100 h
b1101 j
b1 h
b100 [
b100 Y
0'
1&
0-
1,
#2020000
0"
0!
0W
0V
b0 h
b0 j
#2025000
1!
1V
#2030000
0!
0V
#2035000
1!
1V
#2040000
1"
0!
1W
0V
#2045000
1!
1V
b1 h
#2050000
0!
0V
#2055000
1!
1V
b10 h
#2060000
0!
0V
#2065000
1!
1V
b11 h
#2070000
0!
0V
#2075000
1!
1V
b100 h
b11 j
b1 h
b10 Z
b10 X
1$
0#
1*
0)
#2080000
0!
0V
#2085000
1!
1V
b10 h
b100 j
b1 h
b100 Z
b100 X
b1 g
b1 e
b1 Z
b1 X
1L
0J
1R
0P
1%
0$
1+
0*
#2090000
0!
0V
#2095000
1!
1V
b10 h
#2100000
0!
0V
#2105000
1!
1V
b11 h
#2110000
0!
0V
#2115000
1!
1V
b100 h
#2120000
0!
0V
#2125000
1!
1V
b101 h
#2130000
0!
0V
#2135000
1!
1V
b110 h
#2140000
0!
0V
#2145000
1!
1V
b111 h
#2150000
0!
0V
#2155000
1!
1V
b1000 h
#2160000
0!
0V
#2165000
1!
1V
b1001 h
#2170000
0!
0V
#2175000
1!
1V
b1010 h
#2180000
0!
0V
#2185000
1!
1V
b1011 h
#2190000
0!
0V
#2195000
1!
1V
b1100 h
#2200000
0!
0V
#2205000
1!
1V
b1101 h
#2210000
0!
0V
#2215000
1!
1V
b1110 h
#2220000
0!
0V
#2225000
1!
1V
b1111 h
#2230000
0!
0V
#2235000
1!
1V
b10000 h
#2240000
0!
0V
#2245000
1!
1V
b10001 h
#2250000
0!
0V
#2255000
1!
1V
b10010 h
#2260000
0!
0V
#2265000
1!
1V
b10011 h
#2270000
0!
0V
#2275000
1!
1V
b10100 h
#2280000
0!
0V
#2285000
1!
1V
b10101 h
#2290000
0!
0V
#2295000
1!
1V
b10110 h
b10 j
b1 h
b100 g
b100 e
b100 Z
b100 X
b10 Z
b10 X
0%
1$
0+
1*
0L
1J
0R
1P
#2300000
0!
0V
#2305000
1!
1V
b10 h
#2310000
0!
0V
#2315000
1!
1V
b11 h
#2320000
0!
0V
#2325000
1!
1V
b100 h
b1 j
b1 h
b100 Z
b100 X
0$
1#
0*
1)
#2330000
0!
0V
#2335000
1!
1V
b10 h
#2340000
0!
0V
#2345000
1!
1V
b11 h
b111 j
b1 h
b10 ^
b10 b
b10 c
b10 a
1?
0>
1E
0D
1B
0A
16
05
#2350000
0!
0V
#2355000
1!
1V
b10 h
#2360000
0!
0V
#2365000
1!
1V
b11 h
b1000 j
b1 h
b100 c
b100 b
b100 a
b100 ^
b1 ^
b1 b
b1 c
b1 a
17
06
1@
0?
1C
0B
1F
0E
#2370000
0!
0V
#2375000
1!
1V
b10 h
#2380000
0!
0V
#2385000
1!
1V
b11 h
#2390000
0!
0V
#2395000
1!
1V
b100 h
#2400000
0!
0V
#2405000
1!
1V
b101 h
#2410000
0!
0V
#2415000
1!
1V
b110 h
#2420000
0!
0V
#2425000
1!
1V
b111 h
#2430000
0!
0V
#2435000
1!
1V
b1000 h
#2440000
0!
0V
#2445000
1!
1V
b1001 h
#2450000
0!
0V
#2455000
1!
1V
b1010 h
#2460000
0!
0V
#2465000
1!
1V
b1011 h
#2470000
0!
0V
#2475000
1!
1V
b1100 h
b110 j
b1 h
b100 c
b100 b
b100 a
b100 ^
b10 ^
b10 a
b1 b
b1 c
07
16
0@
1?
#2480000
0!
0V
#2485000
1!
1V
b10 h
#2490000
0!
0V
#2495000
1!
1V
b11 h
#2500000
0!
0V
#2505000
1!
1V
b100 h
b101 j
b1 h
b100 c
b100 b
b100 a
b100 ^
b1 c
b1 b
06
15
0?
1>
#2510000
0!
0V
#2515000
1!
1V
b10 h
#2520000
0!
0V
#2525000
1!
1V
b11 h
b1011 j
b1 h
b100 c
b100 b
b10 _
b10 `
b1 c
b1 b
1<
0;
19
08
#2530000
0!
0V
#2535000
1!
1V
b10 h
#2540000
0!
0V
#2545000
1!
1V
b11 h
b1100 j
b1 h
b100 c
b100 b
b100 `
b100 _
b1 _
b1 c
b1 b
b1 `
1:
09
1=
0<
#2550000
0!
0V
#2555000
1!
1V
b10 h
#2560000
0!
0V
#2565000
1!
1V
b11 h
#2570000
0!
0V
#2575000
1!
1V
b100 h
#2580000
0!
0V
#2585000
1!
1V
b101 h
